nspyre/__init__.py
nspyre/cli/__init__.py
nspyre/cli/dataserv.py
nspyre/cli/inserv.py
nspyre/data/__init__.py
nspyre/data/_asyncio_worker.py
nspyre/data/save.py
nspyre/data/server.py
nspyre/data/sink.py
nspyre/data/source.py
nspyre/data/streaming/__init__.py
nspyre/data/streaming/_pickle.py
nspyre/data/streaming/list.py
nspyre/extras/__init__.py
nspyre/extras/subsystem.py
nspyre/gui/__init__.py
nspyre/gui/app.py
nspyre/gui/debug.py
nspyre/gui/images/favicon.ico
nspyre/gui/images/ssssspin.png
nspyre/gui/style/__init__.py
nspyre/gui/style/_colors.py
nspyre/gui/style/_style.py
nspyre/gui/style/style.qss
nspyre/gui/threadsafe.py
nspyre/gui/widgets/__init__.py
nspyre/gui/widgets/_splitter.py
nspyre/gui/widgets/colormap.py
nspyre/gui/widgets/experiment.py
nspyre/gui/widgets/flex_line_plot.py
nspyre/gui/widgets/layout.py
nspyre/gui/widgets/line_plot.py
nspyre/gui/widgets/load.py
nspyre/gui/widgets/main.py
nspyre/gui/widgets/params.py
nspyre/gui/widgets/save.py
nspyre/gui/widgets/separator.py
nspyre/gui/widgets/snake.py
nspyre/gui/widgets/subsystem.py
nspyre/gui/widgets/update_loop.py
nspyre/instrument/__init__.py
nspyre/instrument/gateway.py
nspyre/instrument/manager.py
nspyre/instrument/server.py
nspyre/misc/__init__.py
nspyre/misc/_stacktracer.py
nspyre/misc/logging.py
nspyre/misc/misc.py
nspyre/misc/pint.py
nspyre-0.6.0.1.dist-info/entry_points.txt
nspyre-0.6.0.1.dist-info/LICENSE
nspyre-0.6.0.1.dist-info/WHEEL
nspyre-0.6.0.1.dist-info/METADATA
nspyre-0.6.0.1.dist-info/RECORD
