Metadata-Version: 2.1
Name: nspyre
Version: 0.6.0.1
Summary: Networked Scientific Python Research Environment.
Home-page: https://github.com/nspyre-org/nspyre
License: BSD-3-Clause
Author: Jacob Feder
Author-email: jacobsfeder@gmail.com
Maintainer: Jacob Feder
Maintainer-email: jacobsfeder@gmail.com
Requires-Python: >=3.10,<4.0
Classifier: Intended Audience :: Science/Research
Classifier: License :: OSI Approved :: BSD License
Classifier: Operating System :: MacOS
Classifier: Operating System :: Microsoft :: Windows
Classifier: Operating System :: Unix
Classifier: Programming Language :: Python
Classifier: Programming Language :: Python :: 3
Classifier: Programming Language :: Python :: 3.10
Classifier: Programming Language :: Python :: 3.11
Classifier: Topic :: Scientific/Engineering
Classifier: Topic :: Scientific/Engineering :: Physics
Classifier: Topic :: Scientific/Engineering :: Visualization
Provides-Extra: dev
Requires-Dist: numpy (>=1.23,<2.0)
Requires-Dist: pint; extra == "dev"
Requires-Dist: poetry2setup; extra == "dev"
Requires-Dist: pre-commit; extra == "dev"
Requires-Dist: pyqt6 (>=6.2.3,<7.0.0)
Requires-Dist: pyqtgraph (>=0.13.1,<0.14.0)
Requires-Dist: pytest-cov; extra == "dev"
Requires-Dist: pytest; extra == "dev"
Requires-Dist: rpyc (>=5.2.3,<6.0.0)
Requires-Dist: sphinx-autoapi; extra == "dev"
Requires-Dist: sphinx-copybutton; extra == "dev"
Requires-Dist: sphinx; extra == "dev"
Requires-Dist: sphinx_rtd_theme; extra == "dev"
Project-URL: Bug Tracker, https://github.com/nspyre-org/nspyre/issues
Project-URL: Documentation, https://nspyre.readthedocs.io/
Project-URL: Repository, https://github.com/nspyre-org/nspyre
